{
    "RenderTarget_presets":{
        "1":{
            "preset_name":"gbuffer",
            "size":"MainWindow",
            "RenderTextures":{
		        "tex1":{
		            "attachment":"color0",
		            "preset":"RT_color"
		            },
		        "tex2":{
		            "attachment":"color1",
		            "preset":"RT_color"
		        },
		        "tex3":{
		            "attachment":"color2",
		            "preset":"RT_color_float"
		        },
		        "tex4":{
		            "attachment":"color3",
		            "preset":"RT_color_float"
				},
				"tex5":{
		            "attachment":"color4",
		            "preset":"RT_Mask"
		        },
		        "tex6":{
		            "attachment":"depth",
		            "preset":"RT_depth"
				}
		    }
        },
        "2":{
            "preset_name":"shadow",
            "size":{
                "width":1024,
                "height":1024
            },
            "RenderTextures":{
                "tex1":{
                    "attachment":"depth",
                    "preset":"RT_depth"
                }
            }
        },
        "3":{
            "preset_name":"basic",
            "size":"",
            "RenderTextures":{
                "tex1":{
                    "attachment":"color0",
                    "preset":"RT_color"
                },
                "tex2":{
                    "attachment":"depth",
                    "preset":"RT_depth"

                }
            }
        },

        "4":{
            "preset_name":"basic_linear",
            "size":"",
            "RenderTextures":{
                "tex1":{
                    "attachment":"color0",
                    "preset":"RT_color_linear"
                },
                "tex2":{
                    "attachment":"depth",
                    "preset":"RT_depth"

                }
            }
        },
        "5":{
            "preset_name":"basic_float",
            "size":"",
            "RenderTextures":{
                "tex1":{
                    "attachment":"color0",
                    "preset":"RT_color_float"
                },
                "tex2":{
                    "attachment":"depth",
                    "preset":"RT_depth"

                }
            }
        },
        "6":{
            "preset_name":"RT_2RGBA32",
            "size":"",
            "RenderTextures":{
                "tex1":{
                    "attachment":"color0",
                    "preset":"RT_color_float"
                },
                "tex2":{
                    "attachment":"color1",
                    "preset":"RT_color_float"
                },
                "tex3":{
                    "attachment":"depth",
                    "preset":"RT_depth"

                }
            }
        },
        "7":{
            "preset_name":"RT_opt",
            "size":"",
            "RenderTextures":{
                "tex1":{
                    "attachment":"color0",
                    "preset":"RT_color"
                },
                "tex2":{
                    "attachment":"color1",
                    "preset":"RT_color_float"
                },
                "tex3":{
                    "attachment":"color2",
                    "preset":"RT_color_float"
                },
                "tex4":{
                    "attachment":"depth",
                    "preset":"RT_depth"

                }
            }
        },
        "8":{
            "preset_name":"basic_uint",
            "size":"",
            "RenderTextures":{
                "tex1":{
                    "attachment":"color0",
                    "preset":"RT_color_uint"
                }
            }
        },
        "9":{
            "preset_name":"basic_color_float",
            "size":"",
            "RenderTextures":{
                "tex1":{
                    "attachment":"color0",
                    "preset":"RT_color_float"
                }
            }
        },
        "10":{
            "preset_name":"RT_CSM",
            "size":"",
            "RenderTextures":{
                "tex1":{
                    "attachment":"depth",
                    "preset":"RT_DepthArray"

                }
            }
        },
        "11":{
            "preset_name":"bloom_float",
            "size":"",
            "RenderTextures":{
                "tex1":{
                    "attachment":"color0",
                    "preset":"RT_color_float"
                },
                "tex2":{
                    "attachment":"color1",
                    "preset":"RT_color_float"
                }
            }
        },
        "12":{
            "preset_name":"merge_float",
            "size":"",
            "RenderTextures":{
                "tex1":{
                    "attachment":"color0",
                    "preset":"RT_color_float"
                }
            }
        },
        "13":{
            "preset_name":"RT_LEANmaps",
            "size":"",
            "RenderTextures":{
                "tex1":{
                    "attachment":"color0",
                    "preset":"RT_color_float_linear"
                },
                "tex2":{
                    "attachment":"color1",
                    "preset":"RT_color_float_linear"
                }
            }
        },
        "14":{
            "preset_name":"basic_float_linear",
            "size":"",
            "RenderTextures":{
                "tex1":{
                    "attachment":"color0",
                    "preset":"RT_color_float_linear"
                },
                "tex2":{
                    "attachment":"depth",
                    "preset":"RT_depth"
                }
            }
        },
        "15":{
            "preset_name":"gbuffer2",
            "size":"MainWindow",
            "RenderTextures":{
                "tex1":{
                    "attachment":"color0",
                    "preset":"RT_color"
                },
                "tex2":{
                    "attachment":"color1",
                    "preset":"RT_color_float"
                },
                "tex3":{
                    "attachment":"color2",
                    "preset":"RT_color_float"
                },
                "tex4":{
                    "attachment":"color3",
                    "preset":"RT_color_float"
                },
                "tex5":{
                    "attachment":"depth",
                    "preset":"RT_depth"
                }
            }
        },
        "16":{
			"preset_name":"pbr",
			"size":"",
			"RenderTextures":{
				"tex1":{
					"attachment":"color0",
					"preset":"RT_color"
				},
				"tex2":{
					"attachment":"color1",
					"preset":"RT_color"
				},
				"tex3":{
		            "attachment":"depth",
		            "preset":"RT_depth"
		        }
			}
		}
    }
}
